{
  "source": "寒武纪",
  "layer": "company",
  "updated": "2026-07-20T10:02:33+08:00",
  "items": [
    {
      "title": "寒武纪Q1业绩再创新高 单季度利润超10亿 牛散章建平退出前十大股东 - 财联社",
      "url": "https://news.google.com/rss/articles/CBMiSEFVX3lxTFBZWnloNl9DclJqeDdPOHo2ZjN6Wl95VlB1YlZIQmRwSnkzLWNBcEREdUtGRUpYc3p1RDJDT1JEc1Q0bnNTV0RWUQ?oc=5",
      "summary": "寒武纪Q1业绩再创新高 单季度利润超10亿 牛散章建平退出前十大股东&nbsp;&nbsp;财联社",
      "source": "寒武纪",
      "time": "12h",
      "tags": [],
      "published_at": "2026-07-19T14:00:41+00:00"
    },
    {
      "title": "寒武纪，年内涨超77% - 证券时报",
      "url": "https://news.google.com/rss/articles/CBMiV0FVX3lxTE9OUTAzOHZsOGZhZ0NzaDdqZm5Ec0JObHFiNkl2NERnai0xaXk3RXhkREZ1eWlFcHEzU1FNVjRRV1QyUXJpTXZuUjJCbFk0a0NtR1llb2kwcw?oc=5",
      "summary": "寒武纪，年内涨超77%&nbsp;&nbsp;证券时报",
      "source": "寒武纪",
      "time": "3d",
      "tags": [],
      "published_at": "2026-07-16T15:22:14+00:00"
    }
  ]
}